[
  {
    "code": "0503004",
    "x": 147.4403,
    "y": 249.32387
  },
  {
    "code": "0503005",
    "x": 159.3958,
    "y": 246.08432
  },
  {
    "code": "0503006",
    "x": 171.60199,
    "y": 242.18747
  },
  {
    "code": "0502001",
    "x": 131.62389,
    "y": 197.15908
  },
  {
    "code": "0502002",
    "x": 152.15292,
    "y": 189.83475
  },
  {
    "code": "0502003",
    "x": 169.35308,
    "y": 179.27599
  },
  {
    "code": "0502004",
    "x": 181.74819,
    "y": 165.05272
  },
  {
    "code": "0502005",
    "x": 189.90589,
    "y": 147.19626
  },
  {
    "code": "0502006",
    "x": 195.86335,
    "y": 128.55811
  },
  {
    "code": "0502007",
    "x": 198.1915,
    "y": 110.605
  },
  {
    "code": "0502008",
    "x": 202.37678,
    "y": 88.72289
  },
  {
    "code": "0502009",
    "x": 205.77586,
    "y": 62.59496
  },
  {
    "code": "0502010",
    "x": 202.22101,
    "y": 35.2813
  },
  {
    "code": "0502011",
    "x": 172.80225,
    "y": 35.29229
  },
  {
    "code": "0502012",
    "x": 153.30673,
    "y": 35.13994
  },
  {
    "code": "0502013",
    "x": 134.50271,
    "y": 35.3792
  },
  {
    "code": "0502014",
    "x": 115.17199,
    "y": 35.38994
  },
  {
    "code": "0502015",
    "x": 95.78649,
    "y": 35.40069
  },
  {
    "code": "0502016",
    "x": 76.96147,
    "y": 35.28692
  },
  {
    "code": "0502017",
    "x": 53.72775,
    "y": 34.73955
  },
  {
    "code": "0502023",
    "x": 134.0835,
    "y": 76.55794
  },
  {
    "code": "0502024",
    "x": 115.25848,
    "y": 76.44417
  },
  {
    "code": "0502025",
    "x": 95.91016,
    "y": 76.45495
  },
  {
    "code": "0502026",
    "x": 66.41154,
    "y": 73.64763
  },
  {
    "code": "0502027",
    "x": 72.11359,
    "y": 93.56234
  },
  {
    "code": "0502028",
    "x": 76.96669,
    "y": 111.0389
  },
  {
    "code": "0502029",
    "x": 82.0227,
    "y": 129.32448
  },
  {
    "code": "0502030",
    "x": 89.22029,
    "y": 151.34968
  },
  {
    "code": "0502018",
    "x": 119.46745,
    "y": 139.55347
  },
  {
    "code": "0502019",
    "x": 134.28908,
    "y": 126.37935
  },
  {
    "code": "0502020",
    "x": 146.11885,
    "y": 111.45281
  },
  {
    "code": "0502021",
    "x": 155.7998,
    "y": 94.95699
  },
  {
    "code": "0502022",
    "x": 163.3695,
    "y": 74.43651
  },
  {
    "code": "0503007",
    "x": 184.63066,
    "y": 238.44107
  },
  {
    "code": "0503008",
    "x": 197.13976,
    "y": 235.45154
  },
  {
    "code": "0503009",
    "x": 210.07122,
    "y": 225.47744
  },
  {
    "code": "0503010",
    "x": 220.74461,
    "y": 210.60099
  }
]